byteshieldapisdk/__init__.py
byteshieldapisdk/signer.py
byteshieldapisdk-2.0.0.dist-info/LICENSE
byteshieldapisdk-2.0.0.dist-info/METADATA
byteshieldapisdk-2.0.0.dist-info/WHEEL
byteshieldapisdk-2.0.0.dist-info/top_level.txt
byteshieldapisdk-2.0.0.dist-info/RECORD
