Metadata-Version: 2.1
Name: byteshieldapisdk
Version: 2.0.0
Summary: Api Sdk For Python
Home-page: https://github.com/byteshield-cloud/python.api.sdk.v5
Author: edgenextapisdk
Author-email: edgenextapisdk@outlook.com
Classifier: Programming Language :: Python :: 3
Classifier: License :: OSI Approved :: MIT License
Requires-Python: >=3.5
License-File: LICENSE
